buildPackageTester/__init__.py
buildPackageTester/buildPackageTester.py
buildPackageTester-1.0.5.dist-info/METADATA
buildPackageTester-1.0.5.dist-info/WHEEL
buildPackageTester-1.0.5.dist-info/top_level.txt
buildPackageTester-1.0.5.dist-info/RECORD
