Metadata-Version: 2.1
Name: buildPackageTester
Version: 1.0.5
Summary: 构建包测试
Author: yntense
Author-email: 
